topsis_calculator/__init__.py
topsis_calculator/topsis.py
topsis_sameer_102203785-0.1.0.dist-info/METADATA
topsis_sameer_102203785-0.1.0.dist-info/WHEEL
topsis_sameer_102203785-0.1.0.dist-info/RECORD
