Metadata-Version: 2.4
Name: topsis-sameer-102203785
Version: 0.1.0
Summary: A package to calculate TOPSIS scores from CSV input files
Project-URL: Homepage, https://github.com/yourusername/topsis_calculator
Project-URL: Bug Tracker, https://github.com/yourusername/topsis_calculator/issues
Author-email: Sameer Jain <jainsameer2003@gmail.com>
Classifier: License :: OSI Approved :: MIT License
Classifier: Operating System :: OS Independent
Classifier: Programming Language :: Python :: 3
Requires-Python: >=3.7
Requires-Dist: numpy>=1.20.0
Requires-Dist: pandas>=1.0.0
